{"cameraMode":{"drawMode":0,"name":"Shaded","section":"Shading Mode"},"sceneLighting":true,"audioPlay":false,"sceneViewState":{"m_AlwaysRefresh":false,"showFog":true,"showSkybox":true,"showFlares":true,"showImageEffects":true,"showParticleSystems":true,"showVisualEffectGraphs":true,"m_FxEnabled":true},"in2DMode":false,"pivot":{"x":8.186849594116211,"y":-0.22415590286254884,"z":-0.6816883087158203},"rotation":{"x":-0.26110780239105227,"y":-0.17630040645599366,"z":0.0485745333135128,"w":-0.9478464722633362},"size":2.304191827774048,"orthographic":false}